README.md
setup.py
dcx_utils/__init__.py
dcx_utils/helpers.py
dcx_utils.egg-info/PKG-INFO
dcx_utils.egg-info/SOURCES.txt
dcx_utils.egg-info/dependency_links.txt
dcx_utils.egg-info/requires.txt
dcx_utils.egg-info/top_level.txt