Metadata-Version: 1.2
Name: dcx-utils
Version: 0.1a1
Summary: Support library to be used with Backend frameworks to add support for DCX-UI
Home-page: http://github.com/profmathias/cet-100
Author: Mathias Santos de Brito
Author-email: msbrito@uesc.br
License: MIT
Keywords: dcx
Platform: UNKNOWN
Classifier: Development Status :: 3 - Alpha
Classifier: Intended Audience :: Developers
Classifier: Topic :: Software Development :: Libraries
Classifier: License :: OSI Approved :: MIT License
Classifier: Programming Language :: Python :: 3.6
Classifier: Programming Language :: Python :: 3.7
Classifier: Programming Language :: Python :: 3.8
Classifier: Programming Language :: Python :: 3 :: Only
Requires-Python: >=3.6, <4
